trytond/modules/product/__init__.py
trytond/modules/product/category.py
trytond/modules/product/category.xml
trytond/modules/product/configuration.py
trytond/modules/product/configuration.xml
trytond/modules/product/exceptions.py
trytond/modules/product/message.xml
trytond/modules/product/product.py
trytond/modules/product/product.xml
trytond/modules/product/tryton.cfg
trytond/modules/product/uom.py
trytond/modules/product/uom.xml
trytond/modules/product/icons/tryton-product.svg
trytond/modules/product/locale/bg.po
trytond/modules/product/locale/ca.po
trytond/modules/product/locale/cs.po
trytond/modules/product/locale/de.po
trytond/modules/product/locale/es.po
trytond/modules/product/locale/es_419.po
trytond/modules/product/locale/et.po
trytond/modules/product/locale/fa.po
trytond/modules/product/locale/fi.po
trytond/modules/product/locale/fr.po
trytond/modules/product/locale/hu.po
trytond/modules/product/locale/it.po
trytond/modules/product/locale/lo.po
trytond/modules/product/locale/lt.po
trytond/modules/product/locale/nl.po
trytond/modules/product/locale/pl.po
trytond/modules/product/locale/pt.po
trytond/modules/product/locale/ru.po
trytond/modules/product/locale/sl.po
trytond/modules/product/locale/tr.po
trytond/modules/product/locale/zh_CN.po
trytond/modules/product/tests/__init__.py
trytond/modules/product/tests/scenario_product_identifier.rst
trytond/modules/product/tests/test_product.py
trytond/modules/product/view/category_form.xml
trytond/modules/product/view/category_list.xml
trytond/modules/product/view/category_tree.xml
trytond/modules/product/view/configuration_form.xml
trytond/modules/product/view/identifier_form.xml
trytond/modules/product/view/identifier_list.xml
trytond/modules/product/view/identifier_list_sequence.xml
trytond/modules/product/view/product_form.xml
trytond/modules/product/view/product_form_simple.xml
trytond/modules/product/view/product_tree.xml
trytond/modules/product/view/product_tree_simple.xml
m9s_product-5.2.5.dist-info/LICENSE
m9s_product-5.2.5.dist-info/METADATA
m9s_product-5.2.5.dist-info/WHEEL
m9s_product-5.2.5.dist-info/entry_points.txt
m9s_product-5.2.5.dist-info/top_level.txt
m9s_product-5.2.5.dist-info/RECORD
